{
    "title": "Nachtschicht",
    "artist": "01099",
    "lyrics": "7 Contributors\nNachtschicht Lyrics\n[Songtext zu „Nachtschicht“]\n[Part 1: Paul]\nIch zahl' 'ne Runde beim Warm-up\nViel'n Dank an die Atzen von Warner\nIch hör', mein Nachbar schaut \nTatort\nRoll' auf die Piste, als wär ich beim Radsport\nKomm, pack dein'n Suff ins Gebüsch\nWir kommen zu acht wie ein Kleinbus\nMein Mädchen trinkt mich untern Tisch\nUnd dann trägt sie mich heim, wenn es sein muss, ja\n[Pre-Hook: Paul]\nIch leg' 'ne Nachtschicht ein und brauch' 'ne Haftpflicht, weil\nIch geb' den Laden jetzt zum Abriss frei\nWir geh'n bis acht Uhr steil, ich merk', der Bass fickt rein\n[Hook: Paul & Ikkimel, \nPaul\n, \nIkkimel\n]\nWir hab'n den Suff vorm Club verstеckt\nEin Uhr, der letzte Schluck ist wеg (\nAh\n)\nBis drei war die Mucke wack\nHalb acht geht's heim, werd' im Bus geweckt (\nAh\n)\nWir hab'n den Suff vorm Club versteckt\nEin Uhr, der letzte Schluck ist weg\nBis drei war die Mucke wack\nHalb acht geht's heim, werd' im Bus geweckt (\nIkki\n)\n\n\n\n[Part 2: Ikkimel]\nKeine Ahnung mehr, wie spät, ich bin im Redefluss\nUnd verbringe sehr viel Zeit auf dem Mädchenklo (Ah)\nHab' jetzt zehn neue Boyfriends, es ist ehrenlos\nUnd die sind alle so traurig, wenn ich geh'n muss (Mh)\nIkki das Partyschwein gibt wieder Gas\nWir geh'n wieder rein, kipp' ihr Sekt übern Arsch (Ah)\nHeut keine Fotos, ich bin hier privat\nWer von euch hatt schon mal Sex mit 'nem Star?\nUnd wenn ich ehrlich bin, dann mag ich, wenn es kracht (Mh, mh)\nIch bin bi und fick' auch deine Mutter, wenn es passt (Ah, ah)\n[Pre-Hook: Paul]\nIch leg' 'ne Nachtschicht ein und brauch' 'ne Haftpflicht, weil\nIch geb' den Laden jetzt zum Abriss frei\nWir geh'n bis acht Uhr steil, ich merk', der Bass fickt rein\n(\nIch merk', der Bass fickt rein\n)\n[Hook: Paul & Ikkimel, \nPaul\n]\nWir hab'n den Suff vorm Club versteckt\nEin Uhr, der letzte Schluck ist weg (\nAh\n)\nBis drei war die Mucke wack\nHalb acht geht's heim, werd' im Bus geweckt (\nAh\n)\nWir hab'n den Suff vorm Club versteckt (\nAh\n)\nEin Uhr, der letzte Schluck ist weg (\nAh\n)\nBis drei war die Mucke wack (\nAh\n)\nHalb acht geht's heim, werd' im Bus geweckt\n\n\n\n[Outro: Paul & Ikkimel]\nWir hab'n den Suff vorm Club versteckt\nEin Uhr, der letzte Schluck ist weg",
    "cover_url": "https://images.genius.com/a0126219523d7658f3cfd22957318013.1000x1000x1.png",
    "album": null,
    "year": "2025",
    "genre": null,
    "tags": [],
    "genius_url": "https://genius.com/01099-paul-and-ikkimel-nachtschicht-lyrics"
}