{
    "title": "Schwarz",
    "artist": "LEA",
    "lyrics": "5 Contributors\nSchwarz Lyrics\n[Songtext zu „Schwarz“]\n[Refrain: LEA]\nIch trag' Schwarz, bis es was Dunkleres gibt\nHab' dir zu spät gesagt, was du für mich bist, ja\nHätt nicht gedacht, wie schwer es ohne dich ist\nWerd' nie mehr jemanden so lieben wie dich\nIch trag' Schwarz, bis es was Dunkleres gibt\nFrag' mich die ganze Zeit, wo du grade bist, ja\nHätt nicht gedacht, wie schwer es ohne dich ist\nWerd' nie mehr jemanden so lieben wie dich\n[Strophe 1: LEA]\nKann nicht mehr schlafen, bin seit Tagen wach\nHalt' kaum aus, wie sеhr ich dich und mich verraten hab'\nWill dich vergеssen, doch ich kann das nicht\nWas du bedeutest, weiß ich erst, seit du gegang'n bist\nOhne den Krieg in meinem Kopf\nWärst du vielleicht noch bei mir\nHab' nur an mich gedacht, zu oft\nVerzeih mir\n[Refrain: LEA & \nCasper\n]\nIch trag' Schwarz, bis es was Dunkleres gibt\nHab' dir zu spät gesagt, was du für mich bist, ja\nHätt nicht gedacht, wie schwer es ohne dich ist\nWerd' nie mehr jemanden so lieben wie dich\nIch trag' Schwarz, bis es was Dunkleres gibt\nFrag' mich die ganze Zeit, wo du grade bist, ja\nHätt nicht gedacht, wie schwer es ohne dich ist (\nYeah\n)\nWerd' nie mehr jemanden so lieben wie dich (\nEy\n)\n\n\n\n[Strophe 2: Casper]\nVon „Besser wird's nicht“ zu Fluchen und Krachen\nDoch je heller das Licht, umso dunkler der Schatten\nIch weiß, ich bin viel zu viel für dich\nEin perfekter Sturm, der durch dich fegt, bis nichts mehr übrig ist, typisch ich\nKaum ist alles gut, will ich, dass es splittert und bricht\nProvozier' dich zu Wut, Blicke, Gewitter mit Blitz (Ah)\nVerdreh' danach Worte, bis dir krank und schwindelig ist\nUnd komm', wenn du grad drüber warst, dann mit „Bitte nimm mich zurück“, Shit\nPostkarten aus dem Upside-Down\nWo sich Langzeitgrau schwarz eintaucht\nDich die Angst einsaugt wie gemeinsam in Einzelhaft\nEin Hin und Her, du wirst reisekrank (Scheiße, Mann)\n[Refrain: LEA, \nLEA & Casper\n, \nCasper\n]\nIch trag' Schwarz, bis es was Dunkleres gibt\nHab' dir zu spät gesagt, was du für mich bist, ja\nHätt nicht gedacht, wie schwer es ohne dich ist\nWerd' nie mehr jemanden so lieben wie dich\nIch trag' Schwarz, bis es was Dunkleres gibt (\nDunkleres gibt\n)\nFrag' mich die ganze Zeit, wo du grade bist, ja (\nWo du wohl bist\n)\nHätt nicht gedacht, wie schwer es ohne dich ist\nWerd' nie mehr jemanden so lieben wie dich\n[Outro: Casper]\nIch trag' Schwarz, bis es was Dunkleres gibt\nFrag' mich die ganze Zeit, wo du grade bist\nHätte nicht gedacht, wie schwer es ohne dich ist\nWerd' nie mehr jemanden so lieben wie dich",
    "cover_url": "https://images.genius.com/f9bfe0fc24d7dff64d48c047679d812e.1000x1000x1.png",
    "album": "Fluss",
    "year": "2021",
    "genre": null,
    "tags": [],
    "genius_url": "https://genius.com/Lea-and-casper-schwarz-lyrics"
}